<?xml version="1.0" encoding="utf-8" ?>
<dwsync>
<file name="about.jpg" server="khyo1.cafe24.com//tomcat/webapps/Seowoncar/" local="132560321260000000" remote="132615008400000000" Dst="0" />
<file name="apple-touch-icon.png" server="khyo1.cafe24.com//tomcat/webapps/Seowoncar/" local="132560321260000000" remote="132615008400000000" Dst="0" />
<file name="blog-author.jpg" server="khyo1.cafe24.com//tomcat/webapps/Seowoncar/" local="132560321260000000" remote="132615008400000000" Dst="0" />
<file name="blog-post-1.jpg" server="khyo1.cafe24.com//tomcat/webapps/Seowoncar/" local="132560321260000000" remote="132615008400000000" Dst="0" />
<file name="blog-post-2.jpg" server="khyo1.cafe24.com//tomcat/webapps/Seowoncar/" local="132560321260000000" remote="132615008400000000" Dst="0" />
<file name="blog-post-3.jpg" server="khyo1.cafe24.com//tomcat/webapps/Seowoncar/" local="132560321260000000" remote="132615008400000000" Dst="0" />
<file name="blog-post-4.jpg" server="khyo1.cafe24.com//tomcat/webapps/Seowoncar/" local="132560321260000000" remote="132615008400000000" Dst="0" />
<file name="comments-1.jpg" server="khyo1.cafe24.com//tomcat/webapps/Seowoncar/" local="132560321260000000" remote="132615008400000000" Dst="0" />
<file name="comments-2.jpg" server="khyo1.cafe24.com//tomcat/webapps/Seowoncar/" local="132560321260000000" remote="132615008400000000" Dst="0" />
<file name="comments-3.jpg" server="khyo1.cafe24.com//tomcat/webapps/Seowoncar/" local="132560321260000000" remote="132615008400000000" Dst="0" />
<file name="comments-4.jpg" server="khyo1.cafe24.com//tomcat/webapps/Seowoncar/" local="132560321260000000" remote="132615008400000000" Dst="0" />
<file name="comments-5.jpg" server="khyo1.cafe24.com//tomcat/webapps/Seowoncar/" local="132560321260000000" remote="132615008400000000" Dst="0" />
<file name="comments-6.jpg" server="khyo1.cafe24.com//tomcat/webapps/Seowoncar/" local="132560321260000000" remote="132615008400000000" Dst="0" />
<file name="favicon.png" server="khyo1.cafe24.com//tomcat/webapps/Seowoncar/" local="132560321260000000" remote="132615008400000000" Dst="0" />
<file name="features-1.svg" server="khyo1.cafe24.com//tomcat/webapps/Seowoncar/" local="132560321260000000" remote="132615008400000000" Dst="0" />
<file name="features-2.svg" server="khyo1.cafe24.com//tomcat/webapps/Seowoncar/" local="132560321260000000" remote="132615008400000000" Dst="0" />
<file name="features-3.svg" server="khyo1.cafe24.com//tomcat/webapps/Seowoncar/" local="132560321260000000" remote="132615008400000000" Dst="0" />
<file name="features-4.svg" server="khyo1.cafe24.com//tomcat/webapps/Seowoncar/" local="132560321260000000" remote="132615008400000000" Dst="0" />
<file name="hero-bg.jpg" server="khyo1.cafe24.com//tomcat/webapps/Seowoncar/" local="132560321260000000" remote="132615008400000000" Dst="0" />
<file name="recent-posts-1.jpg" server="khyo1.cafe24.com//tomcat/webapps/Seowoncar/" local="132560321260000000" remote="132615008400000000" Dst="0" />
<file name="recent-posts-2.jpg" server="khyo1.cafe24.com//tomcat/webapps/Seowoncar/" local="132560321260000000" remote="132615008400000000" Dst="0" />
<file name="recent-posts-3.jpg" server="khyo1.cafe24.com//tomcat/webapps/Seowoncar/" local="132560321260000000" remote="132615008400000000" Dst="0" />
<file name="recent-posts-4.jpg" server="khyo1.cafe24.com//tomcat/webapps/Seowoncar/" local="132560321260000000" remote="132615008400000000" Dst="0" />
<file name="recent-posts-5.jpg" server="khyo1.cafe24.com//tomcat/webapps/Seowoncar/" local="132560321260000000" remote="132615008400000000" Dst="0" />
<file name="service-details-1.jpg" server="khyo1.cafe24.com//tomcat/webapps/Seowoncar/" local="132560321260000000" remote="132615008400000000" Dst="0" />
<file name="service-details-2.jpg" server="khyo1.cafe24.com//tomcat/webapps/Seowoncar/" local="132560321260000000" remote="132615008400000000" Dst="0" />
<file name="service-details-3.jpg" server="khyo1.cafe24.com//tomcat/webapps/Seowoncar/" local="132560321260000000" remote="132615008400000000" Dst="0" />
<file name="service-details-4.jpg" server="khyo1.cafe24.com//tomcat/webapps/Seowoncar/" local="132560321260000000" remote="132615008400000000" Dst="0" />
<file name="why-us.jpg" server="khyo1.cafe24.com//tomcat/webapps/Seowoncar/" local="132560321260000000" remote="132615008400000000" Dst="0" />
<file name="why-us.jpg" server="192.168.206.128" local="132560321260000000" remote="132615104400000000" Dst="0" />
<file name="features-1.svg" server="192.168.206.128" local="132560321260000000" remote="132615104400000000" Dst="0" />
<file name="features-2.svg" server="192.168.206.128" local="132560321260000000" remote="132615104400000000" Dst="0" />
<file name="features-3.svg" server="192.168.206.128" local="132560321260000000" remote="132615104400000000" Dst="0" />
<file name="features-4.svg" server="192.168.206.128" local="132560321260000000" remote="132615104400000000" Dst="0" />
</dwsync>